jeepney/__init__.py
jeepney/auth.py
jeepney/bindgen.py
jeepney/bus.py
jeepney/bus_messages.py
jeepney/fds.py
jeepney/low_level.py
jeepney/routing.py
jeepney/wrappers.py
jeepney/integrate/__init__.py
jeepney/integrate/asyncio.py
jeepney/integrate/blocking.py
jeepney/integrate/tornado.py
jeepney/integrate/tests/__init__.py
jeepney/integrate/tests/test_asyncio.py
jeepney/io/__init__.py
jeepney/io/asyncio.py
jeepney/io/blocking.py
jeepney/io/common.py
jeepney/io/threading.py
jeepney/io/tornado.py
jeepney/io/trio.py
jeepney/io/tests/__init__.py
jeepney/io/tests/conftest.py
jeepney/io/tests/test_asyncio.py
jeepney/io/tests/test_blocking.py
jeepney/io/tests/test_threading.py
jeepney/io/tests/test_trio.py
jeepney/io/tests/utils.py
jeepney/tests/__init__.py
jeepney/tests/secrets_introspect.xml
jeepney/tests/test_auth.py
jeepney/tests/test_bindgen.py
jeepney/tests/test_bus.py
jeepney/tests/test_bus_messages.py
jeepney/tests/test_fds.py
jeepney/tests/test_low_level.py
jeepney/tests/test_routing.py
jeepney-0.7.0.dist-info/LICENSE
jeepney-0.7.0.dist-info/WHEEL
jeepney-0.7.0.dist-info/METADATA
jeepney-0.7.0.dist-info/RECORD
