Metadata-Version: 1.1
Name: jeepney
Version: 0.7.0
Summary: Low-level, pure Python DBus protocol wrapper.
Home-page: https://gitlab.com/takluyver/jeepney
Author: Thomas Kluyver
Author-email: thomas@kluyver.me.uk
